unipyAccess/__init__.py
unipyAccess/api_client.py
unipyAccess/hardware.py
unipyAccess/users.py
unipyAccess/utils.py
unipyaccess-0.2.1.dist-info/licenses/LICENSE
unipyaccess-0.2.1.dist-info/METADATA
unipyaccess-0.2.1.dist-info/WHEEL
unipyaccess-0.2.1.dist-info/top_level.txt
unipyaccess-0.2.1.dist-info/RECORD
