Metadata-Version: 2.4
Name: unipyAccess
Version: 0.2.1
License-File: LICENSE
Requires-Dist: requests==2.32.3
Dynamic: description
Dynamic: description-content-type
Dynamic: license-file
Dynamic: requires-dist
